AutomaPy/__init__.py
AutomaPy/examples.py
AutomaPy/help_command.py
AutomaPy/main.py
AutomaPy-1.3.5.dist-info/LICENCE
AutomaPy-1.3.5.dist-info/METADATA
AutomaPy-1.3.5.dist-info/WHEEL
AutomaPy-1.3.5.dist-info/entry_points.txt
AutomaPy-1.3.5.dist-info/top_level.txt
AutomaPy-1.3.5.dist-info/RECORD
