Metadata-Version: 2.1
Name: AutomaPy
Version: 1.3.5
Summary: This package refers to the topic of automata theory, which includes DFA, NDFA, Mealy machines, Moore machines, Finite state machine and Turing machine.
Author: Mohammed Varaliya
Author-email: <mohammedvaraliya2661392@gmail.com>
Keywords: python,DFA,NDFA,Mealy machines,Moore machines,Automata,Theory of Computation,Finite State Machine,Finite Automaton,Turing Machine
Classifier: Development Status :: 5 - Production/Stable
Classifier: Intended Audience :: Developers
Classifier: Programming Language :: Python :: 3
Classifier: Operating System :: Unix
Classifier: Operating System :: MacOS :: MacOS X
Classifier: Operating System :: Microsoft :: Windows
Classifier: Operating System :: POSIX :: Linux
License-File: LICENCE
